nrt_math_utils/__init__.py
nrt_math_utils/common.py
nrt_math_utils/math_utils.py
nrt_math_utils/nrt_numbers.py
nrt_math_utils-1.0.5.data/data/requirements.txt
nrt_math_utils-1.0.5.dist-info/licenses/LICENSE
nrt_math_utils-1.0.5.dist-info/METADATA
nrt_math_utils-1.0.5.dist-info/WHEEL
nrt_math_utils-1.0.5.dist-info/top_level.txt
nrt_math_utils-1.0.5.dist-info/RECORD
