Metadata-Version: 2.4
Name: nrt-math-utils
Version: 1.0.5
Summary: Math utilities in Python
Home-page: https://github.com/etuzon/python-nrt-math-utils
Author: Eyal Tuzon
Author-email: Eyal Tuzon <eyal.tuzon.dev@gmail.com>
Project-URL: Homepage, https://github.com/etuzon/python-nrt-math-utils
Project-URL: Bug Tracker, https://github.com/etuzon/python-nrt-math-utils/issues
Project-URL: documentation, https://github.com/etuzon/python-nrt-math-utils/wiki
Keywords: python,python3,python-3,tool,tools,math,mathematics,utilities,utils,util,nrt,nrt-utils,nrt-utilities,math-utils,math-utilities,nrt-utilities,nrt-math-utils,nrt-math-utilities
Classifier: Programming Language :: Python :: 3
Classifier: Programming Language :: Python :: 3.9
Classifier: Programming Language :: Python :: 3.10
Classifier: Programming Language :: Python :: 3.11
Classifier: Programming Language :: Python :: 3.12
Classifier: Programming Language :: Python :: 3.13
Classifier: Programming Language :: Python :: 3.14
Classifier: Operating System :: OS Independent
Requires-Python: >=3.8
License-File: LICENSE
Requires-Dist: numpy>=1.26.4
Requires-Dist: nrt-collections-utils>=1.0.0
Dynamic: author
Dynamic: home-page
Dynamic: license-file
Dynamic: requires-dist
